morphval/__init__.py
morphval/cli.py
morphval/common.py
morphval/config.py
morphval/validation.py
morphval/validation_main.py
morphval/templates/report_summary_template.jinja2
morphval/templates/report_template.jinja2
morphval/templates/scripts.js
morphval/templates/style.css
synthesis_workflow/__init__.py
synthesis_workflow/circuit.py
synthesis_workflow/fit_utils.py
synthesis_workflow/synthesis.py
synthesis_workflow/tools.py
synthesis_workflow/utils.py
synthesis_workflow/vacuum_synthesis.py
synthesis_workflow/validation.py
synthesis_workflow/_templates/logging.conf
synthesis_workflow/defaults/morphval_default_config.yaml
synthesis_workflow/defaults/score_matrix_default_config.json
synthesis_workflow/extra/__init__.py
synthesis_workflow/extra/insitu_validation.py
synthesis_workflow/extra/make_map.py
synthesis_workflow/tasks/__init__.py
synthesis_workflow/tasks/circuit.py
synthesis_workflow/tasks/cli.py
synthesis_workflow/tasks/config.py
synthesis_workflow/tasks/diametrizer.py
synthesis_workflow/tasks/synthesis.py
synthesis_workflow/tasks/vacuum_synthesis.py
synthesis_workflow/tasks/validation.py
synthesis_workflow/tasks/workflows.py
synthesis_workflow-1.2.1.dist-info/AUTHORS.md
synthesis_workflow-1.2.1.dist-info/LICENSE.txt
synthesis_workflow-1.2.1.dist-info/METADATA
synthesis_workflow-1.2.1.dist-info/WHEEL
synthesis_workflow-1.2.1.dist-info/entry_points.txt
synthesis_workflow-1.2.1.dist-info/top_level.txt
synthesis_workflow-1.2.1.dist-info/RECORD
