Metadata-Version: 2.1
Name: synthesis-workflow
Version: 1.2.1
Summary: Workflow used for synthesis and its validation.
Home-page: https://synthesis-workflow.readthedocs.io
Author: Blue Brain Project, EPFL
License: Apache License 2.0
Project-URL: Tracker, https://github.com/BlueBrain/synthesis-workflow/issues
Project-URL: Source, https://github.com/BlueBrain/synthesis-workflow
Classifier: Development Status :: 2 - Pre-Alpha
Classifier: Intended Audience :: Education
Classifier: Intended Audience :: Science/Research
Classifier: Programming Language :: Python
Classifier: Programming Language :: Python :: 3
Classifier: Programming Language :: Python :: 3.9
Classifier: Programming Language :: Python :: 3.10
Classifier: Programming Language :: Python :: 3.11
Classifier: Programming Language :: Python :: 3.12
Classifier: Topic :: Scientific/Engineering :: Bio-Informatics
Requires-Python: >=3.9
License-File: LICENSE.txt
License-File: AUTHORS.md
Requires-Dist: bluepyparallel >=0.0.8
Requires-Dist: brainbuilder >=0.20.1
Requires-Dist: diameter-synthesis >=0.5.4
Requires-Dist: dictdiffer >=0.9
Requires-Dist: gitpython >=3.1.30
Requires-Dist: jinja2 >=3
Requires-Dist: joblib >=1.2
Requires-Dist: jsonpath-ng >=1.5.3
Requires-Dist: luigi >=3.2
Requires-Dist: luigi-tools >=0.2.1
Requires-Dist: matplotlib >=3.6.2
Requires-Dist: morph-tool <3,>=2.9.1
Requires-Dist: morphio <4,>=3.3.6
Requires-Dist: neuroc <1,>=0.3.0
Requires-Dist: neurocollage >=0.3.6
Requires-Dist: neurom <4,>=3.2.2
Requires-Dist: neurots <4,>=3.6
Requires-Dist: numpy >=1.26.4
Requires-Dist: pandas >=2.1
Requires-Dist: PyYAML >=6
Requires-Dist: region-grower <2,>=1.5.1
Requires-Dist: scipy >=1.13
Requires-Dist: seaborn >=0.12.2
Requires-Dist: tmd >=2.3
Requires-Dist: tqdm >=4.64.1
Requires-Dist: voxcell <4,>=3.1.5
Provides-Extra: docs
Requires-Dist: docutils <0.21 ; extra == 'docs'
Requires-Dist: graphviz ; extra == 'docs'
Requires-Dist: m2r2 ; extra == 'docs'
Requires-Dist: sphinx ; extra == 'docs'
Requires-Dist: sphinx-argparse ; extra == 'docs'
Requires-Dist: sphinx-autoapi ; extra == 'docs'
Requires-Dist: sphinx-bluebrain-theme ; extra == 'docs'
Provides-Extra: test
Requires-Dist: dir-content-diff >=1.9.1 ; extra == 'test'
Requires-Dist: graphviz >=0.14 ; extra == 'test'
Requires-Dist: pandas >=1.5 ; extra == 'test'
Requires-Dist: pytest >=6.2 ; extra == 'test'
Requires-Dist: pytest-console-scripts >=1.3 ; extra == 'test'
Requires-Dist: pytest-cov >=3 ; extra == 'test'
Requires-Dist: pytest-html >=3 ; extra == 'test'
Requires-Dist: pytest-xdist >=3.0.2 ; extra == 'test'
Requires-Dist: matplotlib ==3.6.* ; extra == 'test'
Requires-Dist: seaborn ==0.12.* ; extra == 'test'
